[
  {
    "inputs": [
      {
        "internalType": "address",
        "name": "_listener",
        "type": "address"
      }
    ],
    "name": "getBadge",
    "outputs": [
      {
        "internalType": "uint64",
        "name": "",
        "type": "uint64"
      }
    ],
    "stateMutability": "view",
    "type": "function"
  },
  {
    "inputs": [],
    "name": "pause",
    "outputs": [],
    "stateMutability": "nonpayable",
    "type": "function"
  },
  {
    "inputs": [],
    "name": "unpause",
    "outputs": [],
    "stateMutability": "nonpayable",
    "type": "function"
  },
  {
    "inputs": [
      {
        "internalType": "address",
        "name": "_listener",
        "type": "address"
      },
      {
        "internalType": "uint64",
        "name": "_badge",
        "type": "uint64"
      }
    ],
    "name": "updateBadge",
    "outputs": [],
    "stateMutability": "nonpayable",
    "type": "function"
  }
]
